{"cameraMode":{"drawMode":0,"name":"Shaded","section":"Shading Mode"},"sceneLighting":true,"audioPlay":false,"sceneViewState":{"m_AlwaysRefresh":false,"showFog":true,"showSkybox":true,"showFlares":true,"showImageEffects":true,"showParticleSystems":true,"showVisualEffectGraphs":true,"m_FxEnabled":true},"in2DMode":false,"pivot":{"x":-11.738232612609864,"y":-0.8113024234771729,"z":15.778470039367676},"rotation":{"x":-0.046282362192869189,"y":0.4801580011844635,"z":-0.025381190702319146,"w":-0.8755962252616882},"size":18.43273162841797,"orthographic":false}